odoo/addons/account_analytic_distribution_with_account/README.rst
odoo/addons/account_analytic_distribution_with_account/__init__.py
odoo/addons/account_analytic_distribution_with_account/__manifest__.py
odoo/addons/account_analytic_distribution_with_account/i18n/ca_ES.po
odoo/addons/account_analytic_distribution_with_account/i18n/es.po
odoo/addons/account_analytic_distribution_with_account/models/__init__.py
odoo/addons/account_analytic_distribution_with_account/models/account_analytic_distribution_model.py
odoo/addons/account_analytic_distribution_with_account/readme/CONTRIBUTORS.md
odoo/addons/account_analytic_distribution_with_account/readme/DESCRIPTION.md
odoo/addons/account_analytic_distribution_with_account/readme/USAGE.md
odoo/addons/account_analytic_distribution_with_account/static/description/icon.png
odoo/addons/account_analytic_distribution_with_account/static/description/index.html
odoo/addons/account_analytic_distribution_with_account/views/account_analytic_distribution_views.xml
odoo_addon_account_analytic_distribution_with_account-18.0.1.0.0.1.dist-info/METADATA
odoo_addon_account_analytic_distribution_with_account-18.0.1.0.0.1.dist-info/WHEEL
odoo_addon_account_analytic_distribution_with_account-18.0.1.0.0.1.dist-info/top_level.txt
odoo_addon_account_analytic_distribution_with_account-18.0.1.0.0.1.dist-info/RECORD
